yadokari.py
yadokari-0.1.3.dist-info/DESCRIPTION.rst
yadokari-0.1.3.dist-info/METADATA
yadokari-0.1.3.dist-info/RECORD
yadokari-0.1.3.dist-info/WHEEL
yadokari-0.1.3.dist-info/entry_points.txt
yadokari-0.1.3.dist-info/metadata.json
yadokari-0.1.3.dist-info/top_level.txt
