Metadata-Version: 2.0
Name: yadokari
Version: 0.1.3
Summary: yadokari.py is a command line tool for yadokari reservation system.
Home-page: UNKNOWN
Author: rhoboro
Author-email: rhoboro@gmail.com
License: MIT
Platform: UNKNOWN
Classifier: Programming Language :: Python :: 3
Classifier: Programming Language :: Python :: 3.5
Classifier: Programming Language :: Python :: 3.6
Classifier: License :: OSI Approved :: MIT License
Requires-Dist: Click (<7.0)
Requires-Dist: requests (<3.0)
